ma1522/__init__.py
ma1522/custom_types.py
ma1522/symbolic.py
ma1522/utils.py
ma1522_linear_algebra-1.1.0.dist-info/METADATA
ma1522_linear_algebra-1.1.0.dist-info/WHEEL
ma1522_linear_algebra-1.1.0.dist-info/top_level.txt
ma1522_linear_algebra-1.1.0.dist-info/RECORD
