Metadata-Version: 2.4
Name: ma1522-linear-algebra
Version: 1.1.0
Summary: Python scripts for NUS MA1522 Linear Algebra for Computing
License-Expression: MIT
Classifier: Development Status :: 4 - Beta
Classifier: Intended Audience :: Education
Classifier: Intended Audience :: Science/Research
Classifier: Topic :: Education
Classifier: Topic :: Scientific/Engineering :: Mathematics
Classifier: Programming Language :: Python :: 3 :: Only
Classifier: Programming Language :: Python :: 3.10
Classifier: Programming Language :: Python :: 3.11
Classifier: Programming Language :: Python :: 3.12
Classifier: Programming Language :: Python :: 3.13
Classifier: Programming Language :: Python :: 3.14
Requires-Python: >=3.10
Requires-Dist: numpy>=2.0.2
Requires-Dist: sympy>=1.13.3
Requires-Dist: sympy-latex-parser>=1.9.0
